{
  "uplink": [
    {
      "description": "fPort 1 format 0x14: battery, boot, temp/pressure/RH, lux",
      "input": {
        "fPort": 1,
        "bytes": [20, 29, 67, 35, 17, 25, 82, 95, 151, 174, 1, 2]
      },
      "expected": {
        "data": {
          "make": "mcci",
          "model": "model4832",
          "battery": 4.196,
          "boot": 17,
          "air": {
            "temperature": 25.32,
            "pressure": 978.8,
            "relativeHumidity": 68,
            "lightIntensity": 258
          }
        }
      },
      "source": "ttn-example"
    },
    {
      "description": "unsupported fPort is rejected",
      "input": {
        "fPort": 42,
        "bytes": [20, 1, 24, 0]
      },
      "expected": {
        "errors": ["unsupported fPort 42"]
      },
      "source": "synthetic"
    }
  ],
  "downlink": []
}
