{
  "_note": "Snapshot from TheThingsNetwork/lorawan-devices vendor/te-connectivity/89xxex-codec.yaml (Apache-2.0). Authoring reference only; excluded from the npm tarball.",
  "examples": [
    {
      "description": "Typical vibration data",
      "input": {
        "fPort": 1,
        "bytes": [
          76,
          8,
          235,
          4,
          11,
          0,
          0,
          0,
          9,
          0,
          8,
          0,
          63,
          141,
          1,
          0,
          0,
          2,
          122,
          0,
          0,
          0,
          1,
          226,
          0,
          0,
          0,
          0,
          206,
          3,
          0,
          0,
          0,
          9,
          45,
          0,
          0,
          0,
          11,
          57,
          0,
          0,
          0,
          194,
          7,
          0,
          0,
          0
        ]
      },
      "output": {
        "data": {
          "bat": "76%",
          "peak_nb": 8,
          "temp": 25.9,
          "sig_rms": 0.011,
          "preset": 0,
          "devstat": {
            "acc": "ok",
            "temp": "ok",
            "rotEn": "disabled",
            "com": "ok",
            "battery": "ok"
          },
          "peaks": [
            {
              "freq": 9,
              "mag": 0.008,
              "ratio": 63
            },
            {
              "freq": 397,
              "mag": 0,
              "ratio": 2
            },
            {
              "freq": 122,
              "mag": 0,
              "ratio": 1
            },
            {
              "freq": 226,
              "mag": 0,
              "ratio": 0
            },
            {
              "freq": 974,
              "mag": 0,
              "ratio": 0
            },
            {
              "freq": 11529,
              "mag": 0,
              "ratio": 0
            },
            {
              "freq": 14603,
              "mag": 0,
              "ratio": 0
            }
          ]
        }
      }
    }
  ]
}
