{
  "vendor": "yobiiq",
  "device": "iq-dsmr-lrw",
  "name": "iQ DSMR - Dutch Smart Meter Reader",
  "categories": [
    "climate"
  ],
  "sensors": [
    "temperature",
    "humidity",
    "current",
    "power",
    "voltage",
    "pulse count"
  ],
  "provides": [
    "air.relativeHumidity",
    "air.temperature",
    "battery",
    "batteryPercent",
    "currentL1.data",
    "currentL1.unit",
    "deviceClass",
    "deviceTimestamp",
    "electricityDeliveredToClientT1.data",
    "electricityDeliveredToClientT1.unit",
    "internalCircuitHumidity",
    "internalCircuitTemperature",
    "lastReadingOnChannel1.timestamp",
    "lastReadingOnChannel1.value",
    "powerEvent",
    "voltageL1.data",
    "voltageL1.unit"
  ],
  "variantOf": null,
  "downlink": {
    "encode": false,
    "decode": false
  },
  "ttn": {
    "vendor": "yobiiq",
    "device": "iq-dsmr-lrw",
    "codecId": "iq-dsmr-lrw-codec",
    "codecFile": "iq-dsmr-lrw.js",
    "codecSha256": "62e6ac347c537cb1e3e801056de5493d89c74e331e9c2b86d1342eadd2b948fe",
    "referencedAt": "2026-06-18"
  }
}
